deepbiop-0.1.14.dist-info/METADATA
deepbiop-0.1.14.dist-info/WHEEL
deepbiop-0.1.14.dist-info/licenses/LICENSE
deepbiop.libs/libgcc_s-e52197c3.so.1
deepbiop/fq.pyi
deepbiop/py.typed
deepbiop/core.pyi
deepbiop/utils.pyi
deepbiop/__init__.py
deepbiop/fa.pyi
deepbiop/__init__.pyi
deepbiop/bam.pyi
deepbiop/deepbiop.abi3.so
deepbiop-0.1.14.dist-info/RECORD
